odoo8_addon_website_img_bg_style-8.0.1.0.0.99.dev10-py2.7-nspkg.pth
odoo8_addon_website_img_bg_style-8.0.1.0.0.99.dev10.dist-info/DESCRIPTION.rst
odoo8_addon_website_img_bg_style-8.0.1.0.0.99.dev10.dist-info/METADATA
odoo8_addon_website_img_bg_style-8.0.1.0.0.99.dev10.dist-info/RECORD
odoo8_addon_website_img_bg_style-8.0.1.0.0.99.dev10.dist-info/WHEEL
odoo8_addon_website_img_bg_style-8.0.1.0.0.99.dev10.dist-info/metadata.json
odoo8_addon_website_img_bg_style-8.0.1.0.0.99.dev10.dist-info/namespace_packages.txt
odoo8_addon_website_img_bg_style-8.0.1.0.0.99.dev10.dist-info/top_level.txt
odoo_addons/website_img_bg_style/README.rst
odoo_addons/website_img_bg_style/__init__.py
odoo_addons/website_img_bg_style/__openerp__.py
odoo_addons/website_img_bg_style/i18n/de.po
odoo_addons/website_img_bg_style/i18n/es.po
odoo_addons/website_img_bg_style/i18n/eu.po
odoo_addons/website_img_bg_style/i18n/fr.po
odoo_addons/website_img_bg_style/i18n/gl.po
odoo_addons/website_img_bg_style/i18n/hr.po
odoo_addons/website_img_bg_style/i18n/id.po
odoo_addons/website_img_bg_style/i18n/it.po
odoo_addons/website_img_bg_style/i18n/nl_NL.po
odoo_addons/website_img_bg_style/i18n/pt_BR.po
odoo_addons/website_img_bg_style/i18n/pt_PT.po
odoo_addons/website_img_bg_style/i18n/sl.po
odoo_addons/website_img_bg_style/static/description/icon.png
odoo_addons/website_img_bg_style/static/src/css/styles.css
odoo_addons/website_img_bg_style/static/src/css/styles.css.map
odoo_addons/website_img_bg_style/static/src/css/styles.sass
odoo_addons/website_img_bg_style/views/assets.xml
odoo_addons/website_img_bg_style/views/snippets.xml
